SonicScribe/__init__.py
SonicScribe/main.py
SonicScribe/translate_srt.py
SonicScribe/utils/__init__.py
SonicScribe/utils/audio_extractor.py
SonicScribe/utils/file_manager.py
SonicScribe/utils/language_detector.py
SonicScribe/utils/logger.py
SonicScribe/utils/translator.py
SonicScribe/utils/whisper_api.py
sonicscribe-1.0.3.dist-info/licenses/LICENCE
sonicscribe-1.0.3.dist-info/METADATA
sonicscribe-1.0.3.dist-info/WHEEL
sonicscribe-1.0.3.dist-info/entry_points.txt
sonicscribe-1.0.3.dist-info/top_level.txt
sonicscribe-1.0.3.dist-info/RECORD
