Metadata-Version: 2.4
Name: sonicscribe
Version: 1.0.3
Summary: 🎙️ SonicScribe - Transcribe & Translate audio/video files using Whisper and GPT models.
Home-page: https://github.com/tuklu/SonicScribe.git
Author: Jisnu Kalita
Author-email: ssh@tuklu.dev
Classifier: Programming Language :: Python :: 3
Classifier: License :: OSI Approved :: MIT License
Classifier: Operating System :: OS Independent
Requires-Python: >=3.8
License-File: LICENCE
Requires-Dist: openai>=1.0.0
Requires-Dist: moviepy>=1.0.3
Requires-Dist: python-dotenv>=1.0.0
Requires-Dist: tenacity>=8.0.0
Requires-Dist: rich>=13.0.0
Requires-Dist: pydub>=0.25.1
Requires-Dist: typing-extensions>=4.0.0
Requires-Dist: questionary>=1.10.0
Dynamic: author
Dynamic: author-email
Dynamic: classifier
Dynamic: description
Dynamic: description-content-type
Dynamic: home-page
Dynamic: license-file
Dynamic: requires-dist
Dynamic: requires-python
Dynamic: summary
